jaiminho/__init__.py
jaiminho/admin.py
jaiminho/apps.py
jaiminho/constants.py
jaiminho/models.py
jaiminho/publish_strategies.py
jaiminho/relayer.py
jaiminho/send.py
jaiminho/settings.py
jaiminho/signals.py
jaiminho/views.py
jaiminho/management/__init__.py
jaiminho/management/commands/__init__.py
jaiminho/management/commands/event_cleaner.py
jaiminho/management/commands/events_relay.py
jaiminho/migrations/0001_initial.py
jaiminho/migrations/0002_event_encoder_event_function_signature_event_options.py
jaiminho/migrations/0003_remove_event_action_remove_event_encoder_and_more.py
jaiminho/migrations/0004_event_stream.py
jaiminho/migrations/0005_event_strategy.py
jaiminho/migrations/0006_alter_event_id.py
jaiminho/migrations/0007_alter_event_id_to_bigint.py
jaiminho/migrations/__init__.py
jaiminho/tests/__init__.py
jaiminho/tests/factories.py
jaiminho/tests/test_jaiminho.py
jaiminho/tests/test_models.py
jaiminho/tests/test_settings.py
jaiminho/tests/test_signals.py
jaiminho/tests/utils.py
jaiminho_django_test_project/app/__init__.py
jaiminho_django_test_project/app/apps.py
jaiminho_django_test_project/app/models.py
jaiminho_django_test_project/app/signals.py
jaiminho_django_test_project/app/views.py
jaiminho_django_test_project/app/migrations/__init__.py
jaiminho_django_test_project/management/__init__.py
jaiminho_django_test_project/management/commands/__init__.py
jaiminho_django_test_project/management/commands/validate_event_cleaner.py
jaiminho_django_test_project/management/commands/validate_events_relay.py
jaiminho_django_test_project/tests/__init__.py
jaiminho_django_test_project/tests/test_send.py
jaiminho_django_test_project/tests/management/__init__.py
jaiminho_django_test_project/tests/management/commands/__init__.py
jaiminho_django_test_project/tests/management/commands/test_validate_event_cleaner.py
jaiminho_django_test_project/tests/management/commands/test_validate_relay_events.py
jaiminho_django_test_project/tests_functional/__init__.py
django_jaiminho-1.3.1.dist-info/LICENSE
django_jaiminho-1.3.1.dist-info/METADATA
django_jaiminho-1.3.1.dist-info/WHEEL
django_jaiminho-1.3.1.dist-info/top_level.txt
django_jaiminho-1.3.1.dist-info/RECORD
