Metadata-Version: 2.1
Name: django-jaiminho
Version: 1.3.1
Summary: A broker agnostic implementation of outbox and other message resilience patterns for Django apps
Home-page: https://github.com/loadsmart/django-jaiminho
Author: Loadsmart
Author-email: jaiminho@loadsmart.com
Project-URL: Documentation, https://github.com/loadsmart/django-jaiminho/blob/master/README.md
Project-URL: Source, https://github.com/loadsmart/django-jaiminho
Project-URL: Changelog, https://github.com/loadsmart/django-jaiminho/blob/master/CHANGELOG.md
Classifier: Development Status :: 4 - Beta
Classifier: Intended Audience :: Developers
Classifier: License :: Other/Proprietary License
Classifier: Programming Language :: Python :: 3.8
Classifier: Programming Language :: Python :: 3.9
Classifier: Programming Language :: Python :: 3.10
Classifier: Programming Language :: Python :: 3.11
Classifier: Programming Language :: Python :: 3.12
Requires-Python: >=3.8, <4
License-File: LICENSE
Requires-Dist: Django
Requires-Dist: sentry-sdk
Requires-Dist: dill==0.3.9
